{
    "https://api.github.com/repos/glidejs/glide": {
        "forks": 774,
        "watchers": 7469,
        "stars": 7469,
        "languages": {
            "JavaScript": 114098,
            "SCSS": 3264
        },
        "commits": [
            "2024-11-22T12:00:51Z",
            "2024-11-22T11:59:51Z",
            "2024-11-20T10:48:14Z",
            "2024-11-20T10:45:55Z",
            "2024-07-04T11:19:37Z",
            "2024-07-04T11:16:21Z",
            "2024-07-04T11:14:38Z",
            "2024-05-23T15:39:33Z",
            "2024-05-23T15:37:09Z",
            "2023-09-15T10:14:40Z",
            "2023-09-15T09:49:59Z",
            "2023-07-18T09:12:08Z",
            "2022-09-27T08:26:44Z",
            "2022-09-22T13:04:44Z",
            "2022-05-01T12:22:41Z",
            "2022-03-30T16:36:18Z",
            "2022-02-09T21:55:52Z",
            "2022-01-19T17:40:02Z",
            "2021-11-28T16:23:15Z",
            "2021-11-22T23:18:27Z",
            "2021-11-22T23:15:17Z",
            "2021-11-22T23:03:57Z",
            "2021-11-22T22:54:14Z",
            "2021-11-21T20:12:28Z",
            "2021-11-21T20:11:34Z",
            "2021-11-21T20:09:29Z",
            "2021-11-21T20:09:14Z",
            "2021-11-21T19:12:24Z",
            "2021-11-21T19:09:02Z",
            "2021-11-21T18:15:36Z"
        ],
        "creation_date": "2013-08-19T10:23:34Z",
        "contributors": 30,
        "topics": [
            "carousel",
            "dependency-free",
            "es6",
            "javascript",
            "lightweight",
            "slider"
        ],
        "subscribers": 137,
        "readme": "[![glide.js](https://glidejs.com/images/glidejs-logotype-dark.png)](https://glidejs.com)\n\n### [Glide.js](https://glidejs.com) is a dependency-free JavaScript ES6 slider and carousel. It\u2019s lightweight, flexible and fast. Designed to slide. No less, no more\n\n[![Build Status](https://api.travis-ci.org/glidejs/glide.svg?branch=master)](https://travis-ci.org/glidejs/glide)\n\nWhat can convince you:\n- **Dependency-free**. Everything included, ready for action.\n- Lightweight. Only **~23kb (~7kb gzipped)** with every functionality on board.\n- **Modular**. Remove unused modules and drop script weight even more.\n- **Extendable**. Plug-in your own modules with additional functionalities.\n- **Bundlers ready**. Using Rollup or Webpack? We have your back.\n\n## Documentation\n\nVisit [glidejs.com](https://glidejs.com/docs) for documentation.\n\n> Looking for old documentation? [Wiki](https://github.com/glidejs/glide/wiki) contains archived documentation of Glide.js in version `^2.0.0`.\n\n## Donation\n\nGlide.js is an open source project licensed under the MIT license. It's completely free to use. However, it would be great if you buy me a cup of coffee once in a while to keep me awake :)\n\n- [PayPal](https://www.paypal.me/jedrzejchalubek)\n- [Github Sponsors](https://github.com/sponsors/jedrzejchalubek)\n\n## Getting started\n\nPull-in a latest version with NPM ...\n\n```bash\nnpm install @glidejs/glide\n```\n\n... provide `<link>` to the required core stylesheet. You can also optionally add an included theme stylesheet ...\n\n```html\n<!-- Required Core stylesheet -->\n<link rel=\"stylesheet\" href=\"node_modules/@glidejs/glide/dist/css/glide.core.min.css\">\n\n<!-- Optional Theme stylesheet -->\n<link rel=\"stylesheet\" href=\"node_modules/@glidejs/glide/dist/css/glide.theme.min.css\">\n```\n\n... then, prepare a little bit of necessary markup ...\n\n```html\n<div class=\"glide\">\n  <div data-glide-el=\"track\" class=\"glide__track\">\n    <ul class=\"glide__slides\">\n      <li class=\"glide__slide\"></li>\n      <li class=\"glide__slide\"></li>\n      <li class=\"glide__slide\"></li>\n    </ul>\n  </div>\n</div>\n```\n\n... and finally, initialize and mount a Glide.\n\n```js\nimport Glide from '@glidejs/glide'\n\nnew Glide('.glide').mount()\n```\n\nNeed a few selected modules? Import and mount only what you need.\n\n```js\nimport Glide, { Controls, Breakpoints } from '@glidejs/glide/dist/glide.modular.esm'\n\nnew Glide('.glide').mount({ Controls, Breakpoints })\n```\n\n## Contributing\n\nThe issue channel is especially for improvement proposals and bug reporting. If you have implementing problems, please write on StackOverflow with [glidejs](https://stackoverflow.com/questions/tagged/glidejs) tag.\n\n## Browser Support\n\n - IE 11+\n - Edge\n - Chrome 10+\n - Firefox 10+\n - Opera 15+\n - Safari 5.1+\n - Safari iOS 9+\n\n## Building\n\nBuild using NPM scripts. The following scripts are available:\n- `build:css` - Outputs CSS files from SASS files.\n- `build:js` - Outputs all destination variants of the script.\n- `build` - Comprehensively builds the entire library.\n- `test` - Runs complete test suite.\n- `lint` - Lints library JavaScript files.\n\n## Credits\n\n- [J\u0119drzej Cha\u0142ubek](https://github.com/jedrzejchalubek) - Creator\n- [Contributors](../../contributors)\n\n## License\n\nCopyright (c) 2014-present, [J\u0119drzej Cha\u0142ubek](https://jedrzejchalubek.com). Licensed under the terms of the [MIT License](https://opensource.org/licenses/MIT).\n",
        "releases": [
            {
                "name": "v3.7.1",
                "date": "2024-11-22T12:01:46Z"
            },
            {
                "name": "v3.7.0",
                "date": "2024-11-20T10:49:08Z"
            },
            {
                "name": "v3.6.2",
                "date": "2024-07-04T11:17:29Z"
            },
            {
                "name": "v3.6.1",
                "date": "2023-09-15T10:16:15Z"
            },
            {
                "name": "v3.6.0",
                "date": "2022-09-27T08:30:37Z"
            },
            {
                "name": "v3.5.2",
                "date": "2021-11-28T16:26:50Z"
            },
            {
                "name": "v3.5.1",
                "date": "2021-11-22T23:19:42Z"
            },
            {
                "name": "v3.5.0",
                "date": "2021-11-21T19:23:51Z"
            },
            {
                "name": "v3.4.1",
                "date": "2019-09-23T13:55:52Z"
            },
            {
                "name": "v3.3.0",
                "date": "2019-04-20T20:38:43Z"
            },
            {
                "name": "v3.2.7",
                "date": "2019-03-22T10:22:02Z"
            },
            {
                "name": "v3.2.6",
                "date": "2019-02-10T17:24:07Z"
            },
            {
                "name": "v3.2.5",
                "date": "2019-02-06T18:54:36Z"
            },
            {
                "name": "v3.2.4",
                "date": "2018-11-24T22:32:00Z"
            },
            {
                "name": "v3.2.3",
                "date": "2018-08-08T20:36:07Z"
            },
            {
                "name": "v3.2.2",
                "date": "2018-07-23T18:48:51Z"
            },
            {
                "name": "v3.2.1",
                "date": "2018-07-22T14:22:13Z"
            },
            {
                "name": "v3.2.0",
                "date": "2018-07-16T20:15:54Z"
            },
            {
                "name": "v3.1.0",
                "date": "2018-06-20T11:24:44Z"
            },
            {
                "name": "v3.0.4",
                "date": "2018-05-20T17:54:07Z"
            },
            {
                "name": "v3.0.3",
                "date": "2018-04-30T11:55:11Z"
            },
            {
                "name": "v3.0.2",
                "date": "2018-04-24T18:41:51Z"
            },
            {
                "name": "v3.0.1",
                "date": "2018-04-16T21:30:58Z"
            },
            {
                "name": "v3.0.0",
                "date": "2018-04-03T21:46:43Z"
            },
            {
                "name": "v2.1.0",
                "date": "2017-01-21T17:46:51Z"
            },
            {
                "name": "v2.0.9",
                "date": "2016-08-06T13:39:05Z"
            },
            {
                "name": "v.2.0.8",
                "date": "2016-05-18T06:51:51Z"
            },
            {
                "name": "v2.0.7",
                "date": "2016-03-17T11:09:57Z"
            },
            {
                "name": "v2.0.6",
                "date": "2015-12-21T12:15:13Z"
            },
            {
                "name": "v2.0.5",
                "date": "2015-11-05T20:15:46Z"
            },
            {
                "name": "v2.0.4",
                "date": "2015-09-21T19:52:35Z"
            },
            {
                "name": "v2.0.3",
                "date": "2015-07-21T22:12:34Z"
            },
            {
                "name": "v2.0.2",
                "date": "2015-05-14T16:50:16Z"
            },
            {
                "name": "v2.0.1",
                "date": "2015-04-29T13:45:39Z"
            },
            {
                "name": "v2.0.0",
                "date": "2015-04-22T19:51:00Z"
            },
            {
                "name": "v1.0.7 Old version lastest release",
                "date": "2015-04-22T18:27:43Z"
            },
            {
                "name": "",
                "date": "2014-11-24T23:16:21Z"
            }
        ]
    }
}