{
    "https://api.github.com/repos/matryer/xbar": {
        "forks": 647,
        "watchers": 17636,
        "stars": 17636,
        "languages": {
            "Go": 270924,
            "Objective-C": 85752,
            "HTML": 42827,
            "Svelte": 42693,
            "JavaScript": 9605,
            "Shell": 5385,
            "CSS": 4308,
            "Makefile": 341
        },
        "commits": [
            "2024-09-10T10:18:23Z",
            "2024-09-10T10:18:11Z",
            "2024-09-10T08:09:12Z",
            "2024-09-10T08:08:13Z",
            "2024-09-09T19:31:03Z",
            "2024-08-06T09:44:01Z",
            "2024-08-06T09:30:30Z",
            "2024-08-06T09:24:42Z",
            "2024-08-06T09:12:53Z",
            "2024-08-06T09:10:35Z",
            "2024-08-06T09:07:10Z",
            "2024-08-06T08:57:26Z",
            "2024-08-05T22:36:12Z",
            "2024-08-05T22:24:16Z",
            "2024-08-05T22:18:12Z",
            "2024-08-05T22:15:49Z",
            "2024-08-05T22:13:32Z",
            "2024-08-05T22:12:15Z",
            "2024-08-05T22:10:17Z",
            "2024-08-05T22:09:25Z",
            "2024-08-05T22:05:44Z",
            "2024-08-05T22:04:21Z",
            "2024-08-05T22:01:51Z",
            "2024-08-05T21:58:45Z",
            "2024-08-05T21:57:48Z",
            "2024-08-05T21:55:16Z",
            "2024-08-05T21:53:50Z",
            "2024-08-05T21:51:45Z",
            "2024-08-05T21:50:02Z",
            "2024-08-05T21:17:00Z"
        ],
        "creation_date": "2013-11-13T21:00:12Z",
        "contributors": 30,
        "topics": [
            "bitbar",
            "mac",
            "macos-menu",
            "macosx",
            "menubar",
            "scripting",
            "xbar"
        ],
        "subscribers": 177,
        "readme": "[![](xbarapp.com/public/img/xbar-menu-preview.png)](https://xbarapp.com/)\n\n# Welcome to xbar\n\nxbar (the BitBar reboot) lets you put the output from any script/program in your macOS menu bar.\n\n  * **Complete rewrite from the ground up** - in Go by @matryer and @leaanthony - using [Wails.app (build cross-platform desktop apps using Go & HTML/CSS/JS)](https://wails.app)\n  * Completely open source\n  * [Download latest xbar release](https://github.com/matryer/xbar/releases/latest) - requires macOS Catalina or newer (>= 10.15)\n  * [Visit the app homepage at https://xbarapp.com](https://xbarapp.com)\n  * [Get started](#get-started) and [installing plugins](#installing-plugins)\n\nDigging deeper:\n\n  * [Browse plugin repository](https://xbarapp.com/)\n  * [Guide to writing your own plugins](https://github.com/matryer/xbar-plugins/blob/main/CONTRIBUTING.md)\n\nAnd finally...\n\n  * [Read the story about how xbar unexpectedly got going](https://medium.com/@matryer/what-happens-when-your-old-open-source-project-unexpectedly-gets-to-the-top-of-hacker-news-31114c6c6efb#.fznvtgskb)\n  * [Contributing](#contributing) and [special thanks](#thanks)\n\n## Get started\n\n### Install\n\n* [Download the latest release of xbar](https://github.com/matryer/xbar/releases).\n\n## Installing plugins\n\nFrom an xbar menu, choose **Preferences > Plugins...** to use the xbar app to discover and manage plugins.\n\nYou can [browse all the plugins](https://xbarapp.com/) online, or [write your own](https://github.com/matryer/xbar-plugins/blob/main/CONTRIBUTING.md).\n\n### The Plugin Directory\n\nThe plugin directory is folder on your Mac where the plugins live, located at `~/Library/Application Support/xbar/plugins`.\n\n* If you're transitioning from Bitbar, move your plugins into this new folder to install them\n\n## Contributing\n\nIf you'd like to contribute a plugin, head over to https://github.com/matryer/xbar-plugins to get started.\n\nPlease do not send pull requests to this repo. Open an issue and start a conversation first. PRs will likely not be accepted.\n\n* Get started with our [Writing plugins guide](https://github.com/matryer/xbar-plugins/blob/main/CONTRIBUTING.md)\n\n## Thanks\n\n  * Special thanks to [@leaanthony at https://wails.app](https://wails.app) and [@ianfoo](https://github.com/ianfoo), [@gingerbeardman](https://github.com/gingerbeardman), [@iosdeveloper](https://github.com/iosdeveloper), [@muhqu](https://github.com/muhqu), [@m-cat](https://github.com/m-cat), [@mpicard](https://github.com/mpicard), [@tylerb](https://github.com/tylerb) for their help\n  * Thanks to [Chris Ryer](http://www.chrisryer.co.uk/) for the app logo - and to [@mazondo](https://twitter.com/mazondo) for the original\n  * Thanks for all our [plugin contributors](https://xbarapp.com/) who have come up with some pretty genius things\n",
        "releases": [
            {
                "name": "v2.1.7-beta",
                "date": "2021-10-29T10:42:32Z"
            },
            {
                "name": "v2.1.6-beta",
                "date": "2021-08-28T19:40:24Z"
            },
            {
                "name": "v2.1.5-beta",
                "date": "2021-08-28T11:45:31Z"
            },
            {
                "name": "v2.1.4-beta",
                "date": "2021-07-14T07:47:53Z"
            },
            {
                "name": "v2.1.3-beta",
                "date": "2021-07-12T15:04:59Z"
            },
            {
                "name": "v2.1.0-beta",
                "date": "2021-07-01T12:58:53Z"
            },
            {
                "name": "v2.0.42-beta",
                "date": "2021-04-06T07:59:14Z"
            },
            {
                "name": "v2.0.41-beta",
                "date": "2021-04-05T14:49:59Z"
            },
            {
                "name": "v2.0.40-beta",
                "date": "2021-04-05T10:21:06Z"
            },
            {
                "name": "v2.0.39-beta",
                "date": "2021-04-02T13:14:10Z"
            },
            {
                "name": "v2.0.38-beta",
                "date": "2021-03-31T06:44:25Z"
            },
            {
                "name": "v2.0.37-beta",
                "date": "2021-03-30T12:08:50Z"
            },
            {
                "name": "v2.0.36-beta",
                "date": "2021-03-30T10:48:39Z"
            },
            {
                "name": "v2.0.35-beta",
                "date": "2021-03-29T10:00:15Z"
            },
            {
                "name": "v2.0.34-beta",
                "date": "2021-03-28T08:56:20Z"
            },
            {
                "name": "v2.0.33-beta",
                "date": "2021-03-22T12:39:20Z"
            },
            {
                "name": "v2.0.32-beta",
                "date": "2021-03-19T17:19:37Z"
            },
            {
                "name": "v2.0.31-beta",
                "date": "2021-03-19T10:11:45Z"
            },
            {
                "name": "v2.0.30-beta",
                "date": "2021-03-19T08:56:50Z"
            },
            {
                "name": "v2.0.29-beta",
                "date": "2021-03-18T12:35:59Z"
            },
            {
                "name": "v2.0.28-beta",
                "date": "2021-03-16T16:44:58Z"
            },
            {
                "name": "v2.0.27-beta",
                "date": "2021-03-14T13:32:37Z"
            },
            {
                "name": "v2.0.26-beta",
                "date": "2021-03-13T10:55:08Z"
            },
            {
                "name": "v2.0.25-beta",
                "date": "2021-03-12T12:25:36Z"
            },
            {
                "name": "v2.0.24-beta",
                "date": "2021-03-11T20:32:41Z"
            },
            {
                "name": "v2.0.22-beta",
                "date": "2021-03-11T12:28:56Z"
            },
            {
                "name": "v2.0.21-beta",
                "date": "2021-03-11T11:40:20Z"
            },
            {
                "name": "v2.0.20-beta",
                "date": "2021-03-11T11:36:35Z"
            },
            {
                "name": "v2.0.19-beta",
                "date": "2021-03-10T15:06:35Z"
            },
            {
                "name": "v2.0.17-beta",
                "date": "2021-03-10T14:01:39Z"
            },
            {
                "name": "v2.0.16-beta",
                "date": "2021-03-10T13:38:41Z"
            },
            {
                "name": "v2.0.15-beta",
                "date": "2021-03-10T00:07:31Z"
            },
            {
                "name": "v2.0.14-beta",
                "date": "2021-03-09T23:02:35Z"
            },
            {
                "name": "v2.0.13-beta",
                "date": "2021-03-09T13:22:10Z"
            },
            {
                "name": "v2.0.12-beta",
                "date": "2021-03-09T11:37:04Z"
            },
            {
                "name": "v2.0.10-beta",
                "date": "2021-03-08T23:12:12Z"
            },
            {
                "name": "v2.0.9-beta",
                "date": "2021-03-08T22:48:43Z"
            },
            {
                "name": "v2.0.7-beta",
                "date": "2021-03-08T21:23:57Z"
            },
            {
                "name": "v2.0.6-beta",
                "date": "2021-03-08T20:22:04Z"
            },
            {
                "name": "v2.0.5-beta",
                "date": "2021-03-08T18:57:17Z"
            },
            {
                "name": "v2.0.4.beta",
                "date": "2021-03-08T18:52:40Z"
            },
            {
                "name": "v1.10.1",
                "date": "2020-12-15T17:01:49Z"
            },
            {
                "name": "v1.10.0",
                "date": "2020-12-09T17:30:46Z"
            },
            {
                "name": "v1.9.2",
                "date": "2016-08-30T09:32:04Z"
            },
            {
                "name": "v2 beta 10",
                "date": "2016-08-20T21:15:38Z"
            },
            {
                "name": "v2 beta 9",
                "date": "2016-08-17T06:26:44Z"
            },
            {
                "name": "v2 beta 8",
                "date": "2016-08-16T11:08:59Z"
            },
            {
                "name": "v2 beta 7",
                "date": "2016-07-20T16:10:19Z"
            },
            {
                "name": "v2 beta 6",
                "date": "2016-06-22T13:36:01Z"
            },
            {
                "name": "v2 beta 5",
                "date": "2016-06-18T10:05:16Z"
            },
            {
                "name": "v2 beta 4",
                "date": "2016-05-14T11:36:58Z"
            },
            {
                "name": "v2 beta 3",
                "date": "2016-04-15T13:50:54Z"
            },
            {
                "name": "v2 beta 2",
                "date": "2016-04-13T14:45:13Z"
            },
            {
                "name": "v2 beta 1",
                "date": "2016-04-11T12:05:40Z"
            },
            {
                "name": "v1.9.1",
                "date": "2016-03-29T11:08:06Z"
            },
            {
                "name": "v1.9.0",
                "date": "2016-03-20T19:30:32Z"
            },
            {
                "name": "v1.8.0",
                "date": "2016-03-15T02:55:12Z"
            },
            {
                "name": "v1.7.0",
                "date": "2016-03-12T19:08:27Z"
            },
            {
                "name": "v1.6.0",
                "date": "2016-02-22T22:46:34Z"
            },
            {
                "name": "v1.5.1",
                "date": "2016-02-16T21:50:29Z"
            },
            {
                "name": "v1.5 beta 2",
                "date": "2016-02-10T13:04:59Z"
            },
            {
                "name": "v1.5 beta 1",
                "date": "2016-01-19T16:50:44Z"
            },
            {
                "name": "v1.4",
                "date": "2016-01-10T10:34:35Z"
            },
            {
                "name": "v1.4 beta 2",
                "date": "2016-01-07T15:51:12Z"
            },
            {
                "name": "v1.4 beta",
                "date": "2016-01-06T14:46:53Z"
            },
            {
                "name": "v1.3.1",
                "date": "2015-08-19T09:01:06Z"
            },
            {
                "name": "v1.2",
                "date": "2013-12-30T20:11:44Z"
            },
            {
                "name": "v1.1",
                "date": "2013-12-10T18:55:53Z"
            },
            {
                "name": "v1",
                "date": "2013-11-25T23:29:56Z"
            }
        ]
    }
}