{
    "https://api.github.com/repos/naman14/Timber": {
        "forks": 2157,
        "watchers": 7014,
        "stars": 7014,
        "languages": {
            "Java": 1029405
        },
        "commits": [
            "2020-10-06T05:59:02Z",
            "2020-10-06T05:52:20Z",
            "2020-10-06T05:50:36Z",
            "2020-10-05T19:52:02Z",
            "2020-10-05T19:36:54Z",
            "2020-10-05T19:30:04Z",
            "2020-10-05T18:48:53Z",
            "2020-10-05T18:48:20Z",
            "2020-10-05T18:10:59Z",
            "2020-10-05T14:42:40Z",
            "2020-10-05T14:41:25Z",
            "2020-10-05T14:40:52Z",
            "2019-02-02T09:13:44Z",
            "2018-11-19T18:42:53Z",
            "2018-11-19T06:01:17Z",
            "2018-11-19T05:01:41Z",
            "2018-01-26T15:04:57Z",
            "2018-01-26T15:03:48Z",
            "2018-01-24T21:07:38Z",
            "2018-01-22T16:15:43Z",
            "2018-01-23T21:02:12Z",
            "2018-01-23T20:53:04Z",
            "2018-01-23T16:13:26Z",
            "2018-01-22T19:48:54Z",
            "2018-01-22T16:15:43Z",
            "2018-01-23T17:12:09Z",
            "2018-01-22T17:31:18Z",
            "2018-01-18T21:33:59Z",
            "2018-01-17T14:19:37Z",
            "2017-12-31T18:13:35Z"
        ],
        "creation_date": "2015-06-12T16:43:55Z",
        "contributors": 30,
        "topics": [
            "android",
            "material-design",
            "music-player"
        ],
        "subscribers": 297,
        "readme": "# Timber\n[![Build Status](https://travis-ci.org/naman14/Timber.svg?branch=master)](https://travis-ci.org/naman14/Timber)\n\nMaterial Design Music Player\n\nThis project is no longer in active development. Please refer to [TimberX](https://github.com/naman14/TimberX) instead\n\n<a href='https://play.google.com/store/apps/details?id=naman14.timber&pcampaignid=MKT-Other-global-all-co-prtnr-py-PartBadge-Mar2515-1'><img alt='Get it on Google Play' src='https://play.google.com/intl/en_us/badges/images/generic/en_badge_web_generic.png' height=90px/></a>\n\n<a href='https://f-droid.org/repository/browse/?fdid=naman14.timber'><img alt='Get it on F-Droid' src='https://guardianproject.info/wp-content/uploads/2014/07/logo-fdroid.png' height=60px/></a>\n\n## Screenshots\n\n<img src=\"https://raw.githubusercontent.com/naman14/Timber/master/graphics/screen2.png\" width=\"360\" height=\"640\">\n<img src=\"https://raw.githubusercontent.com/naman14/Timber/master/graphics/screen3.png\" width=\"360\" height=\"640\">\n<img src=\"https://raw.githubusercontent.com/naman14/Timber/master/graphics/screen7.png\" width=\"360\" height=\"640\">\n<img src=\"https://raw.githubusercontent.com/naman14/Timber/master/graphics/screen8.png\" width=\"360\" height=\"640\">\n<img src=\"https://raw.githubusercontent.com/naman14/Timber/master/graphics/screen9.jpg\" width=\"330\" height=\"640\">\n<img src=\"https://raw.githubusercontent.com/naman14/Timber/master/graphics/screen10.jpg\" width=\"330\" height=\"640\">\n<img src=\"https://raw.githubusercontent.com/naman14/Timber/master/graphics/screen1.png\" width=\"360\" height=\"640\">\n<img src=\"https://raw.githubusercontent.com/naman14/Timber/master/graphics/screen5.png\" width=\"360\" height=\"640\">\n<img src=\"https://raw.githubusercontent.com/naman14/Timber/master/graphics/screen12.jpg\" width=\"360\" height=\"640\">\n<img src=\"https://raw.githubusercontent.com/naman14/Timber/master/graphics/screen4.png\" width=\"360\" height=\"640\">\n<img src=\"https://raw.githubusercontent.com/naman14/Timber/master/graphics/screen6.png\" width=\"360\" height=\"640\">\n\n## Features\n- Material design\n- Browse Songs, Albums, Artists\n- Create and edit playlists\n- 6 different now playing styles\n- Homescreen widgets\n- Browse device folders\n- Dark theme and UI customisability\n- Gestures for track switching\n- LastFM scrobble\n- Android Wear and Android Auto support\n- Playing queue in notification (Xposed)\n- Lyrics support\n- Chromecast support\n\n## Changelog\n\nChangelog is available [here](https://github.com/naman14/Timber/blob/master/Changelog.md)\n\n## Credits\n\n* CyanogenMod's [Eleven Music Player](https://github.com/CyanogenMod/android_packages_apps_Eleven)\n* [TimelyTextView](https://github.com/adnan-SM/TimelyTextView)\n* [MultiViewPager](https://github.com/Pixplicity/MultiViewPager)\n* [PlayPauseButton](https://github.com/recruit-lifestyle/PlayPauseButton)\n* [CircularSeekBar](https://github.com/devadvance/circularseekbar)\n* [Nammu](https://github.com/tajchert/Nammu)\n\n# Donate\nPaypal donation email-\nnamandwivedi14@gmail.com\n\n\n## License\n\n>(c) 2015 Naman Dwivedi \n\n>This is free software: you can redistribute it and/or modify it under the terms of the GNU General Public License as published by the Free Software Foundation, either version 3 of the License, or (at your option) any later version. \n\n>This software is distributed in the hope that it will be useful, but WITHOUT ANY WARRANTY; without even the implied warranty of MERCHANTABILITY or FITNESS FOR A PARTICULAR PURPOSE. See the GNU General Public License for more details. \n\n>You should have received a copy of the GNU General Public License along with this app. If not, see <https://www.gnu.org/licenses/>.\n",
        "releases": [
            {
                "name": "Release 1.7",
                "date": "2020-10-05T19:21:55Z"
            },
            {
                "name": "Release 1.6",
                "date": "2017-12-12T17:18:36Z"
            },
            {
                "name": "v15, 0.3b",
                "date": "2016-11-14T11:09:03Z"
            },
            {
                "name": "0.2b",
                "date": "2016-10-31T18:39:30Z"
            },
            {
                "name": "",
                "date": "2016-01-04T05:17:43Z"
            }
        ]
    }
}