{
    "https://api.github.com/repos/sebastianbergmann/php-code-coverage": {
        "forks": 376,
        "watchers": 8855,
        "stars": 8855,
        "languages": {
            "PHP": 615837,
            "HTML": 261244,
            "CSS": 3903,
            "JavaScript": 1224
        },
        "commits": [
            "2025-01-16T08:50:05Z",
            "2025-01-15T13:43:03Z",
            "2025-01-14T13:07:13Z",
            "2025-01-14T08:05:01Z",
            "2025-01-06T08:39:28Z",
            "2025-01-06T08:39:25Z",
            "2025-01-06T08:38:34Z",
            "2025-01-01T10:05:11Z",
            "2025-01-01T10:04:03Z",
            "2025-01-01T10:02:44Z",
            "2025-01-01T10:02:32Z",
            "2025-01-01T09:39:48Z",
            "2025-01-01T09:39:42Z",
            "2025-01-01T09:39:34Z",
            "2024-12-25T08:31:01Z",
            "2024-12-25T08:28:52Z",
            "2024-12-25T08:14:23Z",
            "2024-12-23T14:30:25Z",
            "2024-12-20T16:22:19Z",
            "2024-12-20T06:21:07Z",
            "2024-12-20T06:20:05Z",
            "2024-12-16T10:46:15Z",
            "2024-12-16T10:38:11Z",
            "2024-12-15T08:52:34Z",
            "2024-12-15T08:27:21Z",
            "2024-12-15T08:20:39Z",
            "2024-12-15T06:53:07Z",
            "2024-12-15T06:47:06Z",
            "2024-12-14T16:06:19Z",
            "2024-12-14T16:02:01Z"
        ],
        "creation_date": "2009-05-28T16:01:43Z",
        "contributors": 30,
        "topics": [],
        "subscribers": 56,
        "readme": "# phpunit/php-code-coverage\n\n[![Latest Stable Version](https://poser.pugx.org/phpunit/php-code-coverage/v)](https://packagist.org/packages/phpunit/php-code-coverage)\n[![CI Status](https://github.com/sebastianbergmann/php-code-coverage/workflows/CI/badge.svg)](https://github.com/sebastianbergmann/php-code-coverage/actions)\n[![codecov](https://codecov.io/gh/sebastianbergmann/php-code-coverage/branch/main/graph/badge.svg)](https://codecov.io/gh/sebastianbergmann/php-code-coverage)\n\nProvides collection, processing, and rendering functionality for PHP code coverage information.\n\n## Installation\n\nYou can add this library as a local, per-project dependency to your project using [Composer](https://getcomposer.org/):\n\n```\ncomposer require phpunit/php-code-coverage\n```\n\nIf you only need this library during development, for instance to run your project's test suite, then you should add it as a development-time dependency:\n\n```\ncomposer require --dev phpunit/php-code-coverage\n```\n\n## Usage\n\n```php\n<?php declare(strict_types=1);\nuse SebastianBergmann\\CodeCoverage\\Filter;\nuse SebastianBergmann\\CodeCoverage\\Driver\\Selector;\nuse SebastianBergmann\\CodeCoverage\\CodeCoverage;\nuse SebastianBergmann\\CodeCoverage\\Report\\Html\\Facade as HtmlReport;\n\n$filter = new Filter;\n\n$filter->includeFiles(\n    [\n        '/path/to/file.php',\n        '/path/to/another_file.php',\n    ]\n);\n\n$coverage = new CodeCoverage(\n    (new Selector)->forLineCoverage($filter),\n    $filter\n);\n\n$coverage->start('<name of test>');\n\n// ...\n\n$coverage->stop();\n\n\n(new HtmlReport)->process($coverage, '/tmp/code-coverage-report');\n```\n",
        "releases": [
            {
                "name": "phpunit/php-code-coverage 11.0.8",
                "date": "2024-12-11T12:35:31Z"
            },
            {
                "name": "phpunit/php-code-coverage 11.0.7",
                "date": "2024-10-09T06:23:09Z"
            },
            {
                "name": "phpunit/php-code-coverage 11.0.6",
                "date": "2024-08-22T04:38:41Z"
            },
            {
                "name": "phpunit/php-code-coverage 10.1.16",
                "date": "2024-08-22T04:32:32Z"
            },
            {
                "name": "phpunit/php-code-coverage 9.2.32",
                "date": "2024-08-22T04:24:37Z"
            },
            {
                "name": "phpunit/php-code-coverage 11.0.5",
                "date": "2024-07-03T05:06:08Z"
            },
            {
                "name": "phpunit/php-code-coverage 11.0.4",
                "date": "2024-06-29T08:27:53Z"
            },
            {
                "name": "phpunit/php-code-coverage 10.1.15",
                "date": "2024-06-29T08:25:52Z"
            },
            {
                "name": "phpunit/php-code-coverage 11.0.3",
                "date": "2024-03-12T15:36:13Z"
            },
            {
                "name": "phpunit/php-code-coverage 10.1.14",
                "date": "2024-03-12T15:34:20Z"
            }
        ]
    }
}