{
    "https://api.github.com/repos/TheAlgorithms/Python": {
        "forks": 46156,
        "watchers": 196612,
        "stars": 196612,
        "languages": {
            "Python": 3455813,
            "Shell": 4829,
            "Dockerfile": 406
        },
        "commits": [
            "2025-01-20T20:22:02Z",
            "2025-01-19T07:33:35Z",
            "2025-01-18T03:07:44Z",
            "2025-01-14T21:24:36Z",
            "2025-01-14T20:49:04Z",
            "2025-01-13T20:52:12Z",
            "2025-01-13T20:49:07Z",
            "2025-01-13T01:54:23Z",
            "2025-01-12T23:35:22Z",
            "2025-01-12T16:05:08Z",
            "2025-01-06T20:12:13Z",
            "2024-12-31T02:16:32Z",
            "2024-12-31T02:09:14Z",
            "2024-12-31T01:11:29Z",
            "2024-12-31T00:47:41Z",
            "2024-12-31T00:36:41Z",
            "2024-12-30T20:03:31Z",
            "2024-12-30T19:53:50Z",
            "2024-12-30T19:00:30Z",
            "2024-12-30T15:12:26Z",
            "2024-12-30T15:12:04Z",
            "2024-12-30T15:04:28Z",
            "2024-12-30T12:36:55Z",
            "2024-12-30T11:52:03Z",
            "2024-12-30T11:10:44Z",
            "2024-12-30T10:59:03Z",
            "2024-12-30T10:51:10Z",
            "2024-12-30T10:37:21Z",
            "2024-12-30T10:22:20Z",
            "2024-12-30T09:56:24Z"
        ],
        "creation_date": "2016-07-16T09:44:01Z",
        "contributors": 30,
        "topics": [
            "algorithm",
            "algorithm-competitions",
            "algorithms-implemented",
            "algos",
            "community-driven",
            "education",
            "hacktoberfest",
            "interview",
            "learn",
            "practice",
            "python",
            "searches",
            "sorting-algorithms",
            "sorts"
        ],
        "subscribers": 5937,
        "readme": "<div align=\"center\">\n<!-- Title: -->\n  <a href=\"https://github.com/TheAlgorithms/\">\n    <img src=\"https://raw.githubusercontent.com/TheAlgorithms/website/1cd824df116b27029f17c2d1b42d81731f28a920/public/logo.svg\" height=\"100\">\n  </a>\n  <h1><a href=\"https://github.com/TheAlgorithms/\">The Algorithms</a> - Python</h1>\n<!-- Labels: -->\n  <!-- First row: -->\n  <a href=\"https://gitpod.io/#https://github.com/TheAlgorithms/Python\">\n    <img src=\"https://img.shields.io/badge/Gitpod-Ready--to--Code-blue?logo=gitpod&style=flat-square\" height=\"20\" alt=\"Gitpod Ready-to-Code\">\n  </a>\n  <a href=\"https://github.com/TheAlgorithms/Python/blob/master/CONTRIBUTING.md\">\n    <img src=\"https://img.shields.io/static/v1.svg?label=Contributions&message=Welcome&color=0059b3&style=flat-square\" height=\"20\" alt=\"Contributions Welcome\">\n  </a>\n  <img src=\"https://img.shields.io/github/repo-size/TheAlgorithms/Python.svg?label=Repo%20size&style=flat-square\" height=\"20\">\n  <a href=\"https://the-algorithms.com/discord\">\n    <img src=\"https://img.shields.io/discord/808045925556682782.svg?logo=discord&colorB=7289DA&style=flat-square\" height=\"20\" alt=\"Discord chat\">\n  </a>\n  <a href=\"https://gitter.im/TheAlgorithms/community\">\n    <img src=\"https://img.shields.io/badge/Chat-Gitter-ff69b4.svg?label=Chat&logo=gitter&style=flat-square\" height=\"20\" alt=\"Gitter chat\">\n  </a>\n  <!-- Second row: -->\n  <br>\n  <a href=\"https://github.com/TheAlgorithms/Python/actions\">\n    <img src=\"https://img.shields.io/github/actions/workflow/status/TheAlgorithms/Python/build.yml?branch=master&label=CI&logo=github&style=flat-square\" height=\"20\" alt=\"GitHub Workflow Status\">\n  </a>\n  <a href=\"https://github.com/pre-commit/pre-commit\">\n    <img src=\"https://img.shields.io/badge/pre--commit-enabled-brightgreen?logo=pre-commit&logoColor=white&style=flat-square\" height=\"20\" alt=\"pre-commit\">\n  </a>\n  <a href=\"https://github.com/psf/black\">\n    <img src=\"https://img.shields.io/static/v1?label=code%20style&message=black&color=black&style=flat-square\" height=\"20\" alt=\"code style: black\">\n  </a>\n<!-- Short description: -->\n  <h3>All algorithms implemented in Python - for education</h3>\n</div>\n\nImplementations are for learning purposes only. They may be less efficient than the implementations in the Python standard library. Use them at your discretion.\n\n## Getting Started\n\nRead through our [Contribution Guidelines](CONTRIBUTING.md) before you contribute.\n\n## Community Channels\n\nWe are on [Discord](https://the-algorithms.com/discord) and [Gitter](https://gitter.im/TheAlgorithms/community)! Community channels are a great way for you to ask questions and get help. Please join us!\n\n## List of Algorithms\n\nSee our [directory](DIRECTORY.md) for easier navigation and a better overview of the project.\n",
        "releases": []
    }
}